README.rst
setup.py
xvistaprof/__init__.py
xvistaprof/reader.py
xvistaprof.egg-info/PKG-INFO
xvistaprof.egg-info/SOURCES.txt
xvistaprof.egg-info/dependency_links.txt
xvistaprof.egg-info/not-zip-safe
xvistaprof.egg-info/top_level.txt